{
  "title": "Black Friday Beauty Deals 2025: Dyson Airwrap $150 Off, Shark FlexStyle, NuFACE & More",
  "category": "LIFESTYLE",
  "shortdescription": "Early deals are live – these are the ones editors and celebs are buying right now.",
  "author": "Jane Doe",
  "authorImage": "/images/Author2.webp",
  "date": "November 20, 2025",
  "readingTime": "6 min read",
  "content": [
    {
      "type": "image",
      "content": "/images/Black Friday Beauty Deals 2025 Dyson Airwrap $150 Off.webp"
    },
    {
      "type": "heading",
      "content": "The Deals Dropped Early This Year"
    },
    {
      "type": "paragraph",
      "content": "Black Friday 2025 beauty deals are officially live — and they’re the best we’ve ever seen. Editors, influencers, and celebrities are panic-buying before sellouts."
    },
    {
      "type": "heading",
      "content": "Top Deals Right Now"
    },
    {
      "type": "paragraph",
      "content": "• Dyson Airwrap Complete Long – $449 (was $599) – lowest price ever\n• Shark FlexStyle System – $229 (was $349)\n• NuFACE Trinity+ – $245 (was $395)\n• Solawave 4-in-1 Wand – $99 (was $169)\n• T3 AireBrush Duo – $129 (was $199)\n• CurrentBody LED Mask – 30% off\n• Dr. Dennis Gross SpectraLite FaceWare Pro – $355 (was $455)"
    },
    {
      "type": "paragraph",
      "content": "Pro tip: Dyson and Shark are expected to sell out by Wednesday — don’t wait."
    }
  ]
}